VHDL/Codigo/Ejercicios/myChip.vhd
library ieee;
use ieee.std_logic_1164.all;
---use ieee.std_logic_arith.all;
---use ieee.std_logic_unsigned.all;

entity myChip is
    port (
        a4 : in std_logic;
        a3 : in std_logic;
        a2 : in std_logic;
        a1 : in std_logic;
        a0 : in std_logic;
        p : out std_logic;
        d2 : out std_logic;
        d3 : out std_logic
    );
end myChip;

architecture Behavioral of myChip is
    begin
        p <= (a4 and (not (a3)) and(not(a2)) and(a1)) 
          or (a4 and (not (a3)) and (a1) and (a0)) 
          or (a4 and (not (a3)) and (a1) and (a0))
          or (a4 and (a3) and (a2) and (a0)) 
          or (not (a3) and (a2) and (a1) and (a0))
          or (not (a4) and (a3) and (not (a2)) and (a1) and (a0))
          or (not (a4) and (not (a3)) and (not (a2)) and (a1));
        
        d2 <= not (a0);

        d3 <= ((not a4) and(not a3) and(not a2) and(not a1) and(not a0))
           or ((not a4) and(not a3) and( not a2) and(a1) and(a0))
           or ((not a4) and a3 and (not a2) and (not a1) and a0)
           or ((not a4) and a3 and (not a2) and (not a1) and a0)
           or ((not a4) and a3 and a2 and (not a1) and (not a0))
           or ((not a4) and a3 and a2 and a1 and a0)
           or ((a4 and (not a3) and (not a2) and a1 and (not a0)))
           or ((a4 and (not a3) and (not a2) and (not a1) and a0))
           or (a4 and (not a3) and a2 and ( not a1) and a0)
           or (a4 and a3 and (not a2) and a1 and a0)
           or (a4 and a3 and a2 and a1 and (not a0));
        
    end Behavioral;

VHDL/Codigo/myChip_tb.vhd
library ieee;
use ieee.std_logic_1164.all;
---use ieee.std_logic_arth.all;
---use ieee.std_logic_unsigned.all;

entity myChip_tb is
end entity;

architecture myChip_tb of myChip_tb is
    component myChip
    port (
        a4 : in std_logic;
        a3 : in std_logic;
        a2 : in std_logic;
        a1 : in std_logic;
        a0 : in std_logic;
        p : out std_logic;
        d2 : out std_logic;
        d3 : out std_logic
    );
    end component;

    signal a4 : std_logic;
    signal a3 : std_logic;
    signal a2 : std_logic;
    signal a1 : std_logic;
    signal a0 : std_logic;
    signal p : std_logic;
    signal d2 : std_logic;
    signal d3 : std_logic;
    
begin
    uut: myChip
    port map(
            a4 => a4,
            a3 => a3,
            a2 => a2,
            a1 => a1,
            a0 => a0,
            p => p,
            d2 => d2,
            d3 => d3
    );

    process
    begin
    wait for 10 ns;
    a4 <= '1'; a3 <= '0'; a2 <= '1'; a1 <= '0'; a0 <= '0'; 
    --- 10100 = 20 
    wait for 10 ns;
    a4 <= '0'; a3 <= '0'; a2 <= '0'; a1 <= '0'; a0 <= '1'; 
    --- 00001 = 1
    wait for 10 ns;
    a4 <= '1'; a3 <= '0'; a2 <= '1'; a1 <= '1'; a0 <= '0'; 
    --- 10110 = 22
    wait for 10 ns;
    a4 <= '0'; a3 <= '0'; a2 <= '0'; a1 <= '1'; a0 <= '1'; 
    -- 00011 = 3
    wait for 10 ns;
    a4 <= '1'; a3 <= '1'; a2 <= '0'; a1 <= '0'; a0 <= '0'; 
    --- 11000 = 24
    wait for 10 ns;
    a4 <= '0'; a3 <= '1'; a2 <= '0'; a1 <= '0'; a0 <= '1'; 
    --- 01001 = 9
    wait for 10 ns;
    a4 <= '1'; a3 <= '1'; a2 <= '1'; a1 <= '1'; a0 <= '0'; 
    --- 11110 = 30
    wait for 10 ns;
    a4 <= '0'; a3 <= '1'; a2 <= '0'; a1 <= '1'; a0 <= '1'; 
    --- 01011 = 11
    wait for 10 ns;
    wait;
    end process;
end architecture;

VHDL/Codigo/Ejercicios/myChip_tb.vcd
$date
  Wed Apr 13 08:21:12 2022
$end
$version
  GHDL v0
$end
$timescale
  1 fs
$end
$scope module standard $end
$upscope $end
$scope module std_logic_1164 $end
$upscope $end
$scope module mychip_tb $end
$var reg 1 ! a4 $end
$var reg 1 " a3 $end
$var reg 1 # a2 $end
$var reg 1 $ a1 $end
$var reg 1 % a0 $end
$var reg 1 & p $end
$var reg 1 ' d2 $end
$var reg 1 ( d3 $end
$scope module uut $end
$var reg 1 ) a4 $end
$var reg 1 * a3 $end
$var reg 1 + a2 $end
$var reg 1 , a1 $end
$var reg 1 - a0 $end
$var reg 1 . p $end
$var reg 1 / d2 $end
$var reg 1 0 d3 $end
$upscope $end
$upscope $end
$enddefinitions $end
#0
U!
U"
U#
U$
U%
U&
U'
U(
U)
U*
U+
U,
U-
U.
U/
U0
#10000000
1!
0"
1#
0$
0%
0&
1'
0(
1)
0*
1+
0,
0-
0.
1/
00
#20000000
0!
0#
1%
0'
0)
0+
1-
0/
#30000000
1!
1#
1$
0%
1'
1)
1+
1,
0-
1/
#40000000
0!
0#
1%
1&
0'
1(
0)
0+
1-
1.
0/
10
#50000000
1!
1"
0$
0%
0&
1'
0(
1)
1*
0,
0-
0.
1/
00
#60000000
0!
1%
0'
1(
0)
1-
0/
10
#70000000
1!
1#
1$
0%
1'
1)
1+
1,
0-
1/
#80000000
0!
0#
1%
1&
0'
0(
0)
0+
1-
1.
0/
00
