VHDL/Codigo/Ejercicios/flip-flops/tipo JK/tipoJK.vhd
library ieee;
use ieee.std_logic_1164.all;
---use ieee.std_logic_arth.all;
---use ieee.std_logic_unsigned.all;

entity tipoJK is
    port(
      RST : in std_logic;
      D : in std_logic;
      Q : out std_logic;
      noQ : out std_logic;
      CLK : in std_logic
    );
end tipoJK;

architecture Behavioral of tipoJK is
    signal internalQ : std_logic;
    begin
        process (CLK)
        begin
            if CLK'event and CLK='1' then
                if(RST='1'AND D = '1') then
                    internalQ <= (NOT internalQ);
                    else if(RST = '1') then
                        internalQ <= '0';
                        else
                        internalQ <= D;
                    end if;
                end if;
            end if;
            end process;
        Q <= internalQ;
        noQ <= (NOT internalQ);
    end Behavioral;

VHDL/Codigo/Ejercicios/flip-flops/tipo JK/tipoJK_tb.vhd
library ieee;
use ieee.std_logic_1164.all;
---use ieee.std_logic_arth.all;
---use ieee.std_logic_unsigned.all;

entity tipoJK_tb is
end entity;

architecture tipoJK_tb of tipoJK_tb is
    component tipoJK
    port(
        RST : in std_logic;
        D : in std_logic;
        Q : out std_logic;
        noQ : out std_logic;
        CLK : in std_logic
      );
    end component;
    
    signal RST : std_logic;
    signal D : std_logic;
    signal Q : std_logic;
    signal noQ : std_logic;
    signal CLK : std_logic;
    
    begin
        uut: tipoJK
        port map(
            RST => RST,
            D => D,
            Q => Q,
            noQ => noQ,
            CLK => CLK
        );
    process 
    begin
    wait for 10 ns;
    CLK <= '1'; D <= '1';
    wait for 10 ns;
    CLK <= '0';
    wait for 10 ns;
    CLK <= '0'; D <= '0';
    wait for 10 ns;
    CLK <= '0';
    wait for 10 ns;
    CLK <= '1'; D <= '1';
    wait for 10 ns;
    CLK <= '0';
    wait for 10 ns;
    CLK <= '0'; D <= '0';
    wait for 10 ns;
    CLK <= '0';
    wait for 10 ns;
    CLK <= '1'; RST <= '1';
    wait for 10 ns;
    CLK <= '0';
    wait for 10 ns;
    CLK <= '1'; D <= '1'; RST <= '1';
    wait for 10 ns;
    CLK <= '0';
    wait for 10 ns;
    CLK <= '1'; D <= '1'; RST <= '0';
    wait for 10 ns;
    CLK <= '0';
    wait for 10 ns;
    CLK <= '1'; D <= '0'; RST <= '0';
    wait for 10 ns;
    wait;
    end process;
end architecture;

VHDL/Codigo/Ejercicios/flip-flops/tipo JK/tipoJK_tb.vcd
$date
  Wed Jun  8 15:49:15 2022
$end
$version
  GHDL v0
$end
$timescale
  1 fs
$end
$scope module standard $end
$upscope $end
$scope module std_logic_1164 $end
$upscope $end
$scope module tipojk_tb $end
$var reg 1 ! rst $end
$var reg 1 " d $end
$var reg 1 # q $end
$var reg 1 $ noq $end
$var reg 1 % clk $end
$scope module uut $end
$var reg 1 & rst $end
$var reg 1 ' d $end
$var reg 1 ( q $end
$var reg 1 ) noq $end
$var reg 1 * clk $end
$var reg 1 + internalq $end
$upscope $end
$upscope $end
$enddefinitions $end
#0
U!
U"
U#
U$
U%
U&
U'
U(
U)
U*
U+
#10000000
1"
1#
0$
1%
1'
1(
0)
1*
1+
#20000000
0%
0*
#30000000
0"
0'
#40000000
#50000000
1"
1%
1'
1*
#60000000
0%
0*
#70000000
0"
0'
#80000000
#90000000
1!
0#
1$
1%
1&
0(
1)
1*
0+
#100000000
0%
0*
#110000000
1"
1#
0$
1%
1'
1(
0)
1*
1+
#120000000
0%
0*
#130000000
0!
1%
0&
1*
#140000000
0%
0*
#150000000
0"
0#
1$
1%
0'
0(
1)
1*
0+
