VHDL/Codigo/TPs/TP6/Contar2.vhd
library ieee;
use ieee.std_logic_1164.all;

entity Contar2 is
port(
    COUNT  : out std_logic_vector(2 downto 0) := "000";
    UP_LOW : in std_logic := '1'; --FALLING_EDGE IS 0, RISING_EDGE IS 1 | DEFAULT & RESET = '1'
    RST    : in std_logic := '0';
    CLK    : in std_logic := '0'
);
end entity;

architecture sens of Contar2 is

    signal INTERNAL_COUNT : std_logic_vector(2 downto 0) := "000";

    --Maquina de Estados

    signal CRNT_STATE : std_logic_vector(3 downto 0);
    signal NEXT_STATE : std_logic_vector(3 downto 0);

    --Estados

    Constant IDLE  : std_logic_vector(3 downto 0) := "0001";
    Constant CHECK : std_logic_vector(3 downto 0) := "0010";
    Constant SUM   : std_logic_vector(3 downto 0) := "0100";
    Constant RESET : std_logic_vector(3 downto 0) := "1000";

    begin

    STATE_MACHINE:process(NEXT_STATE)
    begin                            
        if NEXT_STATE'event then
            CRNT_STATE <= NEXT_STATE;
        end if;
    end process;

    MAIN_PROCESS:process(CLK)
        begin
        if (falling_edge(CLK) and UP_LOW = '0') or (rising_edge(CLK) and UP_LOW = '1') then
            case CRNT_STATE is
                when IDLE =>
                    if RST = '1' then
                        NEXT_STATE <= RESET;
                    else
                        NEXT_STATE <= SUM;
                    end if;
                when SUM =>
                    if INTERNAL_COUNT = "000" and RST = '0' then
                        INTERNAL_COUNT <= "010" ;
                        COUNT <= "010";
                        NEXT_STATE <= SUM;
                    elsif INTERNAL_COUNT = "010" and RST = '0' then
                        INTERNAL_COUNT <= "100" ;
                        COUNT <= "100";
                        NEXT_STATE <= SUM;
                    elsif INTERNAL_COUNT = "100" and RST = '0' then
                        INTERNAL_COUNT <= "110" ;
                        COUNT <= "110";
                        NEXT_STATE <= SUM;
                    elsif INTERNAL_COUNT = "110" and RST = '0' then
                        INTERNAL_COUNT <= "000" ;
                        COUNT <= "000";
                        NEXT_STATE <= SUM;
                    elsif RST = '1' then
                        NEXT_STATE <= RESET;
                    end if;
                when RESET =>
                    INTERNAL_COUNT <= "000" ;
                    COUNT <= "000";
                    NEXT_STATE <= IDLE;
                when others =>
                    NEXT_STATE <= RESET;
                end case;
            end if;
        end process;
end architecture;

VHDL/Codigo/TPs/TP6/Contar2_tb.vhd
library ieee;
use ieee.std_logic_1164.all;

entity Contar2_tb is
end entity;

architecture tb of Contar2_tb is
    component Contar2
    port(
        COUNT  : out std_logic_vector(2 downto 0) := "000";
        UP_LOW : in std_logic := '1'; --FALLING_EDGE IS 0, RISING_EDGE IS 1 | DEFAULT & RESET = '1'
        RST    : in std_logic := '0';
        CLK    : in std_logic := '0'
    );
    end component;

    signal COUNT  : std_logic_vector(2 downto 0) := "000";
    signal UP_LOW : std_logic := '1'; --FALLING_EDGE IS 0, RISING_EDGE IS 1 | DEFAULT & RESET = '1'
    signal RST    : std_logic := '0';
    signal CLK    : std_logic := '0';

    constant clk_period : time := 1 ns;

begin

    uut: Contar2
    port map(
        COUNT   => COUNT,
        UP_LOW  => UP_LOW,
        RST     => RST,
        CLK     => CLK
    );

    clk_process :process
        variable contadorTB : integer range 0 to 50 := 0;
        begin
        contadorTB := contadorTB + 1;
        if contadorTB < 49 then 
            CLK <= '0';
            wait for clk_period/2;  --for 0.5 ns signal is '0'.
            CLK <= '1';
            wait for clk_period/2;  --for next 0.5 ns signal is '1'.
        else
        wait;
        end if;
   end process;

   tb_process :process
        --VARS AND SIGNALS:

        begin
            wait for 5 ns;
            UP_LOW <= '0';
            wait for 5 ns;
            RST <= '1';
            wait for 2 ns;
            RST <= '0';

            wait for 5 ns;
            UP_LOW <= '1';
            wait for 5 ns;
            RST <= '1';
            wait for 2 ns;
            RST <= '0';

            wait for 30 ns;
            RST <= '1';
            wait for 2 ns;
            RST <= '0';
        wait;
    end process;
        
end architecture;

VHDL/Codigo/TPs/TP6/Contar2_tb.vcd
$date
  Mon Jun 27 17:40:17 2022
$end
$version
  GHDL v0
$end
$timescale
  1 fs
$end
$scope module standard $end
$upscope $end
$scope module std_logic_1164 $end
$upscope $end
$scope module contar2_tb $end
$var reg 3 ! count[2:0] $end
$var reg 1 " up_low $end
$var reg 1 # rst $end
$var reg 1 $ clk $end
$scope module uut $end
$var reg 3 % count[2:0] $end
$var reg 1 & up_low $end
$var reg 1 ' rst $end
$var reg 1 ( clk $end
$var reg 3 ) internal_count[2:0] $end
$var reg 4 * crnt_state[3:0] $end
$var reg 4 + next_state[3:0] $end
$upscope $end
$upscope $end
$enddefinitions $end
#0
b000 !
1"
0#
0$
b000 %
1&
0'
0(
b000 )
bUUUU *
bUUUU +
#500000
1$
1(
b1000 *
b1000 +
#1000000
0$
0(
#1500000
1$
1(
b0001 *
b0001 +
#2000000
0$
0(
#2500000
1$
1(
b0100 *
b0100 +
#3000000
0$
0(
#3500000
b010 !
1$
b010 %
1(
b010 )
#4000000
0$
0(
#4500000
b100 !
1$
b100 %
1(
b100 )
#5000000
b110 !
0"
0$
b110 %
0&
0(
b110 )
#5500000
1$
1(
#6000000
b000 !
0$
b000 %
0(
b000 )
#6500000
1$
1(
#7000000
b010 !
0$
b010 %
0(
b010 )
#7500000
1$
1(
#8000000
b100 !
0$
b100 %
0(
b100 )
#8500000
1$
1(
#9000000
b110 !
0$
b110 %
0(
b110 )
#9500000
1$
1(
#10000000
1#
0$
1'
0(
b1000 *
b1000 +
#10500000
1$
1(
#11000000
b000 !
0$
b000 %
0(
b000 )
b0001 *
b0001 +
#11500000
1$
1(
#12000000
0#
0$
0'
0(
b0100 *
b0100 +
#12500000
1$
1(
#13000000
b010 !
0$
b010 %
0(
b010 )
#13500000
1$
1(
#14000000
b100 !
0$
b100 %
0(
b100 )
#14500000
1$
1(
#15000000
b110 !
0$
b110 %
0(
b110 )
#15500000
1$
1(
#16000000
b000 !
0$
b000 %
0(
b000 )
#16500000
1$
1(
#17000000
1"
0$
1&
0(
#17500000
b010 !
1$
b010 %
1(
b010 )
#18000000
0$
0(
#18500000
b100 !
1$
b100 %
1(
b100 )
#19000000
0$
0(
#19500000
b110 !
1$
b110 %
1(
b110 )
#20000000
0$
0(
#20500000
b000 !
1$
b000 %
1(
b000 )
#21000000
0$
0(
#21500000
b010 !
1$
b010 %
1(
b010 )
#22000000
1#
0$
1'
0(
#22500000
1$
1(
b1000 *
b1000 +
#23000000
0$
0(
#23500000
b000 !
1$
b000 %
1(
b000 )
b0001 *
b0001 +
#24000000
0#
0$
0'
0(
#24500000
1$
1(
b0100 *
b0100 +
#25000000
0$
0(
#25500000
b010 !
1$
b010 %
1(
b010 )
#26000000
0$
0(
#26500000
b100 !
1$
b100 %
1(
b100 )
#27000000
0$
0(
#27500000
b110 !
1$
b110 %
1(
b110 )
#28000000
0$
0(
#28500000
b000 !
1$
b000 %
1(
b000 )
#29000000
0$
0(
#29500000
b010 !
1$
b010 %
1(
b010 )
#30000000
0$
0(
#30500000
b100 !
1$
b100 %
1(
b100 )
#31000000
0$
0(
#31500000
b110 !
1$
b110 %
1(
b110 )
#32000000
0$
0(
#32500000
b000 !
1$
b000 %
1(
b000 )
#33000000
0$
0(
#33500000
b010 !
1$
b010 %
1(
b010 )
#34000000
0$
0(
#34500000
b100 !
1$
b100 %
1(
b100 )
#35000000
0$
0(
#35500000
b110 !
1$
b110 %
1(
b110 )
#36000000
0$
0(
#36500000
b000 !
1$
b000 %
1(
b000 )
#37000000
0$
0(
#37500000
b010 !
1$
b010 %
1(
b010 )
#38000000
0$
0(
#38500000
b100 !
1$
b100 %
1(
b100 )
#39000000
0$
0(
#39500000
b110 !
1$
b110 %
1(
b110 )
#40000000
0$
0(
#40500000
b000 !
1$
b000 %
1(
b000 )
#41000000
0$
0(
#41500000
b010 !
1$
b010 %
1(
b010 )
#42000000
0$
0(
#42500000
b100 !
1$
b100 %
1(
b100 )
#43000000
0$
0(
#43500000
b110 !
1$
b110 %
1(
b110 )
#44000000
0$
0(
#44500000
b000 !
1$
b000 %
1(
b000 )
#45000000
0$
0(
#45500000
b010 !
1$
b010 %
1(
b010 )
#46000000
0$
0(
#46500000
b100 !
1$
b100 %
1(
b100 )
#47000000
0$
0(
#47500000
b110 !
1$
b110 %
1(
b110 )
#48000000
#54000000
1#
1'
#56000000
0#
0'
