VHDL/Codigo/Ejercicios/tp3ej8/sieteSegmentos.vhd
library ieee;
use ieee.std_logic_1164.all;
---use ieee.std_logic_arith.all;
---use ieee.std_logic_unsigned.all;

entity sieteSegmentos is
    port (
        AIN : in std_logic;
        BIN : in std_logic;
        CIN : in std_logic;
        DIN : in std_logic;
        LT : in std_logic;
        BI : in std_logic;
        a : out std_logic;
        b : out std_logic;
        c : out std_logic;
        d : out std_logic;
        e : out std_logic;
        f : out std_logic;
        g : out std_logic
    );
end sieteSegmentos;

architecture Behavioral of sieteSegmentos is
    begin
        a <= ((NOT BI) AND (LT)) OR ( (NOT BI) AND (---BI LT PRIORITY CHECK
             ((NOT AIN) AND (CIN))
          OR ((NOT AIN) AND (NOT BIN) AND (NOT DIN))
          OR ((NOT AIN) AND (BIN) AND (DIN))
          OR ((AIN) AND (NOT BIN) AND (NOT CIN))));
        
        b <= ((NOT BI) AND (LT)) OR ( (NOT BI) AND ( ---BI LT PRIORITY CHECK
             ((NOT AIN) AND (NOT BIN))
          OR ((NOT BIN) AND (NOT CIN))
          OR ((NOT AIN) AND (NOT CIN) AND (NOT DIN))
          OR ((NOT AIN) AND (CIN) AND (DIN))));

        c <= ((NOT BI) AND (LT)) OR ( (NOT BI) AND ( ---BI LT PRIORITY CHECK
             ((NOT BIN) AND (NOT CIN))
          OR ((NOT AIN) AND (DIN))
          OR ((NOT AIN) AND (BIN))));

        d <= ((NOT BI) AND (LT)) OR ( (NOT BI) AND ( ---BI LT PRIORITY CHECK
             ((NOT BIN) AND (NOT CIN) AND (NOT DIN))
          OR ((NOT AIN) AND (NOT BIN) AND (CIN))
          OR ((NOT AIN) AND (CIN) AND (NOT DIN))
          OR ((NOT AIN) AND (BIN) AND (NOT CIN) AND (DIN))));

        e <= ((NOT BI) AND (LT)) OR ( (NOT BI) AND ( ---BI LT PRIORITY CHECK
             ((NOT BIN) AND (NOT CIN) AND (NOT DIN))
          OR ((NOT AIN) AND (CIN) AND (NOT DIN))));

        f <= ((NOT BI) AND (LT)) OR ( (NOT BI) AND ( ---BI LT PRIORITY CHECK
             ((NOT AIN) AND (NOT CIN) AND (NOT DIN))
          OR ((NOT AIN) AND (BIN) AND (NOT CIN))
          OR ((NOT AIN) AND (BIN) AND (NOT DIN))
          OR ((AIN) AND (NOT BIN) AND (NOT CIN))));

        g <= ((NOT BI) AND (LT)) OR ( (NOT BI) AND ( ---BI LT PRIORITY CHECK
             ((NOT AIN) AND (NOT BIN) AND (CIN))
          OR ((NOT AIN) AND (CIN) AND (NOT DIN))
          OR ((NOT AIN) AND (BIN) AND (NOT CIN))
          OR ((AIN) AND (NOT BIN) AND (NOT CIN))));
    end Behavioral;

VHDL/Codigo/Ejercicios/tp3ej8/sieteSegmentos_tb.vhd
library ieee;
use ieee.std_logic_1164.all;
---use ieee.std_logic_arth.all;
---use ieee.std_logic_unsigned.all;

entity sieteSegmentos_tb is
end entity;

architecture sieteSegmentos_tb of sieteSegmentos_tb is
    component sieteSegmentos
    port (
        AIN : in std_logic;
        BIN : in std_logic;
        CIN : in std_logic;
        DIN : in std_logic;
        LT : in std_logic;
        BI : in std_logic;
        a : out std_logic;
        b : out std_logic;
        c : out std_logic;
        d : out std_logic;
        e : out std_logic;
        f : out std_logic;
        g : out std_logic
    );
    end component;

    signal a : std_logic;
    signal b : std_logic;
    signal c : std_logic;
    signal d : std_logic;
    signal e : std_logic;
    signal f : std_logic;
    signal g : std_logic;
    signal AIN : std_logic;
    signal BIN : std_logic;
    signal CIN : std_logic;
    signal DIN : std_logic;
    signal LT : std_logic;
    signal BI : std_logic;
    
begin
    uut: sieteSegmentos
    port map(
            DIN => DIN,
            CIN => CIN,
            BIN => BIN,
            AIN => AIN,
            LT => LT,
            BI => BI,
            a => a,
            b => b,
            c => c,
            d => d,
            e => e,
            f => f,
            g => g
    );

    process
    begin
    wait for 10 ns;
    DIN <= '0'; CIN <= '0'; BIN <= '0'; AIN <= '0'; BI <= '0'; LT <= '0';
    --- Cero
    wait for 10 ns;
    DIN <= '0'; CIN <= '0'; BIN <= '0'; AIN <= '1'; BI <= '0'; LT <= '0';
    --- Uno
    wait for 10 ns;
    DIN <= '0'; CIN <= '0'; BIN <= '1'; AIN <= '0'; BI <= '0'; LT <= '0';
    --- Dos
    wait for 10 ns;
    DIN <= '0'; CIN <= '0'; BIN <= '1'; AIN <= '1'; BI <= '0'; LT <= '0';
    -- Tres
    wait for 10 ns;
    DIN <= '0'; CIN <= '1'; BIN <= '0'; AIN <= '0'; BI <= '0'; LT <= '0';
    --- Cuatro
    wait for 10 ns;
    DIN <= '0'; CIN <= '1'; BIN <= '0'; AIN <= '1'; BI <= '0'; LT <= '0';
    --- Cinco
    wait for 10 ns;
    DIN <= '0'; CIN <= '1'; BIN <= '1'; AIN <= '0'; BI <= '0'; LT <= '0';
    --- Seis
    wait for 10 ns;
    DIN <= '0'; CIN <= '1'; BIN <= '1'; AIN <= '1'; BI <= '0'; LT <= '0';
    --- Siete
    wait for 10 ns;
    DIN <= '1'; CIN <= '0'; BIN <= '0'; AIN <= '0'; BI <= '0'; LT <= '0';
    --- Ocho
    wait for 10 ns;
    DIN <= '1'; CIN <= '0'; BIN <= '0'; AIN <= '1'; BI <= '0'; LT <= '0';
    --- Nueve
    wait for 10 ns;
    DIN <= '1'; CIN <= '0'; BIN <= '1'; AIN <= '0'; BI <= '0'; LT <= '0';
    --- Diez
    wait for 10 ns;
    DIN <= '1'; CIN <= '0'; BIN <= '1'; AIN <= '1'; BI <= '0'; LT <= '0';
    --- Once
    wait for 10 ns;
    DIN <= '1'; CIN <= '1'; BIN <= '0'; AIN <= '0'; BI <= '0'; LT <= '0';
    --- Doce
    wait for 10 ns;
    DIN <= '1'; CIN <= '1'; BIN <= '0'; AIN <= '1'; BI <= '0'; LT <= '0';
    --- Trece
    wait for 10 ns;
    DIN <= '1'; CIN <= '1'; BIN <= '1'; AIN <= '0'; BI <= '0'; LT <= '0';
    --- Catorce
    wait for 10 ns;
    DIN <= '1'; CIN <= '1'; BIN <= '1'; AIN <= '1'; BI <= '0'; LT <= '0';
    --- Cince
    wait for 10 ns;
    DIN <= '0'; CIN <= '1'; BIN <= '1'; AIN <= '1'; BI <= '0'; LT <= '1';
    --- Siete con LT
    wait for 10 ns;
    DIN <= '0'; CIN <= '1'; BIN <= '1'; AIN <= '1'; BI <= '1'; LT <= '0';
    --- Siete con BI
    wait for 10 ns;
    DIN <= '0'; CIN <= '1'; BIN <= '1'; AIN <= '1'; BI <= '1'; LT <= '1';
    --- Siete con LT y BI
    wait for 10 ns;
    wait;
    end process;
end architecture;

VHDL/Codigo/Ejercicios/tp3ej8/sieteSegmentos_tb.vcd
$date
  Sun May  1 11:15:18 2022
$end
$version
  GHDL v0
$end
$timescale
  1 fs
$end
$scope module standard $end
$upscope $end
$scope module std_logic_1164 $end
$upscope $end
$scope module sietesegmentos_tb $end
$var reg 1 ! a $end
$var reg 1 " b $end
$var reg 1 # c $end
$var reg 1 $ d $end
$var reg 1 % e $end
$var reg 1 & f $end
$var reg 1 ' g $end
$var reg 1 ( ain $end
$var reg 1 ) bin $end
$var reg 1 * cin $end
$var reg 1 + din $end
$var reg 1 , lt $end
$var reg 1 - bi $end
$scope module uut $end
$var reg 1 . ain $end
$var reg 1 / bin $end
$var reg 1 0 cin $end
$var reg 1 1 din $end
$var reg 1 2 lt $end
$var reg 1 3 bi $end
$var reg 1 4 a $end
$var reg 1 5 b $end
$var reg 1 6 c $end
$var reg 1 7 d $end
$var reg 1 8 e $end
$var reg 1 9 f $end
$var reg 1 : g $end
$upscope $end
$upscope $end
$enddefinitions $end
#0
U!
U"
U#
U$
U%
U&
U'
U(
U)
U*
U+
U,
U-
U.
U/
U0
U1
U2
U3
U4
U5
U6
U7
U8
U9
U:
#10000000
1!
1"
1#
1$
1%
1&
0'
0(
0)
0*
0+
0,
0-
0.
0/
00
01
02
03
14
15
16
17
18
19
0:
#20000000
1'
1(
1.
1:
#30000000
0!
0$
0%
0(
1)
0.
1/
04
07
08
#40000000
0"
0#
0&
0'
1(
1.
05
06
09
0:
#50000000
1!
1"
1$
1%
1'
0(
0)
1*
0.
0/
10
14
15
17
18
1:
#60000000
0!
0"
0$
0%
0'
1(
1.
04
05
07
08
0:
#70000000
1!
1#
1$
1%
1&
1'
0(
1)
0.
1/
14
16
17
18
19
1:
#80000000
0!
0#
0$
0%
0&
0'
1(
1.
04
06
07
08
09
0:
#90000000
1"
1#
0(
0)
0*
1+
0.
0/
00
11
15
16
#100000000
1!
1&
1'
1(
1.
14
19
1:
#110000000
0"
1$
0(
1)
0.
1/
05
17
#120000000
0!
0#
0$
0&
0'
1(
1.
04
06
07
09
0:
#130000000
1!
1"
1#
1$
1'
0(
0)
1*
0.
0/
10
14
15
16
17
1:
#140000000
0!
0"
0#
0$
0'
1(
1.
04
05
06
07
0:
#150000000
1!
1"
1#
0(
1)
0.
1/
14
15
16
#160000000
0!
0"
0#
1(
1.
04
05
06
#170000000
1!
1"
1#
1$
1%
1&
1'
0+
1,
01
12
14
15
16
17
18
19
1:
#180000000
0!
0"
0#
0$
0%
0&
0'
0,
1-
02
13
04
05
06
07
08
09
0:
#190000000
1,
12
